phylogenetics/__init__.py
phylogenetics/blast2fasta.py
phylogenetics/cli.py
phylogenetics/phylogenetics.py
phylogenetics/phylotree.py
phylogenetics/venn.py
phylogenetics/templates/gitignore
phylogenetics/templates/heatmap_config.txt
phylogenetics/templates/heatmap_template.html
phylogenetics/templates/limits.txt
phylogenetics/templates/proteinlist.txt
phylogenetics/templates/tree_config.txt
phylogenetics/templates/tree_to_prune.txt
VisProPhyl-0.0.2.dist-info/LICENSE
VisProPhyl-0.0.2.dist-info/METADATA
VisProPhyl-0.0.2.dist-info/WHEEL
VisProPhyl-0.0.2.dist-info/entry_points.txt
VisProPhyl-0.0.2.dist-info/top_level.txt
VisProPhyl-0.0.2.dist-info/RECORD
