Metadata-Version: 2.1
Name: VisProPhyl
Version: 0.0.2
Summary: Map Blast results on a common-knowledge phylogenetic tree
Home-page: https://github.com/MolecularBioinformatics/VisProPhyl
Author: Mathias Bockwoldt
Author-email: mathias.bockwoldt@gmail.com
Classifier: Programming Language :: Python :: 3 :: Only
Classifier: Programming Language :: Python :: 3.6
Classifier: Programming Language :: Python :: 3.7
Classifier: Programming Language :: Python :: 3.8
Classifier: Programming Language :: Python :: 3.9
Classifier: Programming Language :: Python :: 3.10
Classifier: License :: OSI Approved :: MIT License
Classifier: Operating System :: OS Independent
Classifier: Development Status :: 4 - Beta
Classifier: Intended Audience :: Science/Research
Classifier: Natural Language :: English
Classifier: Topic :: Scientific/Engineering :: Bio-Informatics
Requires-Python: >=3.6
License-File: LICENSE
Requires-Dist: PyQt5 >=5.11.3
Requires-Dist: wheel >=0.33.0
Requires-Dist: numpy >=1.15.1
Requires-Dist: scipy >=1.11.0
Requires-Dist: matplotlib >=3.1.1
Requires-Dist: pandas >=1.0.0
Requires-Dist: Pillow >=6.0.0
Requires-Dist: biopython >=1.7.4
Requires-Dist: ete3 >=3.1.1
Requires-Dist: taxfinder >=0.0.1
